ur_py_ctl/__init__.py
ur_py_ctl/ur_socket_client.py
ur_py_ctl/urscript_commands.py
ur_py_ctl-0.1.7.dist-info/LICENSE
ur_py_ctl-0.1.7.dist-info/WHEEL
ur_py_ctl-0.1.7.dist-info/METADATA
ur_py_ctl-0.1.7.dist-info/RECORD
