Metadata-Version: 2.1
Name: ur-py-ctl
Version: 0.1.7
Summary: Python wrapper around URScript (for Universal Robotics robots).
Home-page: https://gitlab.control.lth.se/robotlab/ur_py_ctl
Author: Anton Tetov
Author-email: anton@tetov.se
Requires-Python: >=3.9,<3.11
Classifier: Programming Language :: Python :: 3
Classifier: Programming Language :: Python :: 3.9
Classifier: Programming Language :: Python :: 3.10
Requires-Dist: importlib_metadata (>=1.0,<2.0); python_version < "3.8"
Project-URL: Repository, https://gitlab.control.lth.se/robotlab/ur_py_ctl
